zonolayer/__init__.py
zonolayer/core.py
zonolayer/version.py
zonolayer/zonotope.py
zonolayer-0.3.1.dist-info/licenses/LICENSE
zonolayer-0.3.1.dist-info/METADATA
zonolayer-0.3.1.dist-info/WHEEL
zonolayer-0.3.1.dist-info/top_level.txt
zonolayer-0.3.1.dist-info/RECORD
