Metadata-Version: 2.4
Name: zonolayer
Version: 0.3.1
Summary: Last-layer uncertainty modeling via zonotopic representations.
Author: Matthew McCann, Marco De Angelis
License-Expression: MIT
Project-URL: Homepage, https://github.com/MattCodes03/zonolayer
Project-URL: Repository, https://github.com/MattCodes03/zonolayer
Project-URL: Bug Tracker, https://github.com/MattCodes03/zonolayer/issues
Requires-Python: >=3.9
License-File: LICENSE
Requires-Dist: numpy
Requires-Dist: torch
Requires-Dist: matplotlib
Requires-Dist: PyIPM
Requires-Dist: scipy
Dynamic: license-file
